MasterQuotePy/__init__.py
MasterQuotePy/model.py
MasterQuotePy/quote.py
MasterQuotePy-0.0.17.dist-info/LICENSE.txt
MasterQuotePy-0.0.17.dist-info/METADATA
MasterQuotePy-0.0.17.dist-info/WHEEL
MasterQuotePy-0.0.17.dist-info/top_level.txt
MasterQuotePy-0.0.17.dist-info/RECORD
