Metadata-Version: 2.1
Name: MasterQuotePy
Version: 0.0.17
Summary: MasterLink TWSE/TAIFEX API package
Home-page: UNKNOWN
Author: SYLIN
Author-email: sylin@masterlink.com.tw
License: UNKNOWN
Platform: UNKNOWN
Classifier: Programming Language :: Python :: 3
Classifier: License :: OSI Approved :: MIT License
Classifier: Operating System :: OS Independent
Requires-Python: >=3.8
License-File: LICENSE.txt
